{
  "schemaVersion": 1,
  "id": "alchemicalwonders",
  "version": "${version}",
  "name": "Alchemical Wonders",
  "description": "",
  "authors": [],
  "contact": {},
  "license": "MIT",
  "icon": "assets/alchemicalwonders/icon.png",
  "environment": "*",
  "entrypoints": {
    "client": [
      "com.emptybottlemods.alchemicalwonders.client.AlchemicalWondersClient"
    ],
    "main": [
      "com.emptybottlemods.alchemicalwonders.AlchemicalWonders"
    ]
  },
  "mixins": [
    "alchemicalwonders.mixins.json"
  ],
  "depends": {
    "fabricloader": ">=0.12.2",
    "fabric": "*",
    "minecraft": "1.17.1"
  }
}
